budgitree/__init__.py
budgitree/__main__.py
budgitree/data/__init__.py
budgitree/data/example_tree.tree
budgitree/tests/__init__.py
budgitree/tests/budgitree_test.py
budgitree/tests/test_suite.py
budgitree-0.0.9.dist-info/LICENSE
budgitree-0.0.9.dist-info/METADATA
budgitree-0.0.9.dist-info/WHEEL
budgitree-0.0.9.dist-info/entry_points.txt
budgitree-0.0.9.dist-info/top_level.txt
budgitree-0.0.9.dist-info/RECORD
