Metadata-Version: 2.1
Name: budgitree
Version: 0.0.9
Summary: Budgitree newick tree processor
Home-page: https://github.com/schultzm/budgitree
Author: Dr Mark B Schultz
Author-email: dr.mark.schultz@gmail.com
License: UNKNOWN
Project-URL: Bug Reports, https://github.com/schultzm/budgitree/issues
Project-URL: Source, https://github.com/schultzm/budgitree/
Keywords: budgitree scientific exponential notation branch support decimal polytomy polytomies phylogenetic newick tree bifurcating
Platform: UNKNOWN
Classifier: Development Status :: 3 - Alpha
Classifier: Intended Audience :: Developers
Classifier: Topic :: Software Development :: Build Tools
Classifier: License :: OSI Approved :: MIT License
Classifier: Programming Language :: Python :: 3.7
Requires-Python: >=3.7
Requires-Dist: ete3 (>=3.1.1)
Requires-Dist: biopython (>=1.74)
Requires-Dist: six (>=1.13.0)
Provides-Extra: dev
Requires-Dist: pre-commit ; extra == 'dev'
Requires-Dist: pipenv ; extra == 'dev'
Provides-Extra: test
Requires-Dist: pytest ; extra == 'test'
Requires-Dist: pytest-cov ; extra == 'test'
